mkcrack/__init__.py
mkcrack/__main__.py
mkcrack/cracker.py
mkcrack-0.1.2.dist-info/LICENSE
mkcrack-0.1.2.dist-info/METADATA
mkcrack-0.1.2.dist-info/WHEEL
mkcrack-0.1.2.dist-info/top_level.txt
mkcrack-0.1.2.dist-info/RECORD
