Metadata-Version: 2.1
Name: mkcrack
Version: 0.1.2
Summary: A simple Yescrypt hash cracker by Manju
Author: Manju
Author-email: kotabagimanju240@gmail.com
Requires-Python: >=3.6
License-File: LICENSE
